Workbook

Sheet Job
A1: Job setup
A2: Fill in the yellow cells. Budget lines go on the Budget tab.
A4: Job number | C4: e.g. 26-014
A5: Job name* | C5: Required
A6: GC / client | C6: Matched to your Clients & GCs list
A7: Location
A8: Project manager | C8: Name or email of a Project Manager login
A9: Start date
A10: End date
A11: Contract amount | C11: Leave blank to use the total bid price
A12: Budget structure | B12: Bid items | C12: Bid items or Cost codes
A13: Default overhead % | B13: 0.1 | C13: Taken out of every line’s bid price unless the line has its own
A14: Default markup % | B14: 0.12 | C14: Taken out of every line’s bid price unless the line has its own
A16: Totals (calculated)
A17: Total bid price | B17: =SUM(Budget!J2:J400) | C17: What the job was bid at
A18: Overhead + markup | B18: =SUM(Budget!O2:O400) | C18: Taken out of the bid
A19: Budget cost | B19: =SUM(Budget!P2:P400) | C19: What the job has to be built for
A20: Contract used | B20: =IF(B11<>"",B11,B17) | C20: Contract amount if entered, otherwise total bid price
A21: Budgeted profit | B21: =B20-B19
A22: Budgeted margin | B22: =IF(B20=0,0,B21/B20)

Sheet Budget
A1: Item no.* | B1: Description* | C1: Unit | D1: Quantity | E1: Labor — bid | F1: Equipment — bid | G1: Materials — bid | H1: Subcontract — bid | I1: Other — bid | J1: Bid price | K1: Overhead % (line) | L1: Markup % (line) | M1: Overhead % used | N1: Markup % used | O1: OH + markup $ | P1: Budget cost | Q1: Labor — budget | R1: Equipment — budget | S1: Materials — budget | T1: Subcontract — budget | U1: Other — budget | V1: Unit bid price | W1: Unit cost | X1: Notes
J2: =IF(COUNT(E2:I2)=0,"",SUM(E2:I2)) | M2: =IF(J2="","",IF(K2<>"",K2,N(Job!$B$13))) | N2: =IF(J2="","",IF(L2<>"",L2,N(Job!$B$14))) | O2: =IF(J2="","",J2-P2) | P2: =IF(J2="","",J2/((1+M2)*(1+N2))) | Q2: =IF(J2="","",N(E2)/((1+M2)*(1+N2))) | R2: =IF(J2="","",N(F2)/((1+M2)*(1+N2))) | S2: =IF(J2="","",N(G2)/((1+M2)*(1+N2))) | T2: =IF(J2="","",N(H2)/((1+M2)*(1+N2))) | U2: =IF(J2="","",N(I2)/((1+M2)*(1+N2))) | V2: =IF(OR(J2="",N(D2)=0),"",J2/D2) | W2: =IF(OR(J2="",N(D2)=0),"",P2/D2)
J3: =IF(COUNT(E3:I3)=0,"",SUM(E3:I3)) | M3: =IF(J3="","",IF(K3<>"",K3,N(Job!$B$13))) | N3: =IF(J3="","",IF(L3<>"",L3,N(Job!$B$14))) | O3: =IF(J3="","",J3-P3) | P3: =IF(J3="","",J3/((1+M3)*(1+N3))) | Q3: =IF(J3="","",N(E3)/((1+M3)*(1+N3))) | R3: =IF(J3="","",N(F3)/((1+M3)*(1+N3))) | S3: =IF(J3="","",N(G3)/((1+M3)*(1+N3))) | T3: =IF(J3="","",N(H3)/((1+M3)*(1+N3))) | U3: =IF(J3="","",N(I3)/((1+M3)*(1+N3))) | V3: =IF(OR(J3="",N(D3)=0),"",J3/D3) | W3: =IF(OR(J3="",N(D3)=0),"",P3/D3)
J4: =IF(COUNT(E4:I4)=0,"",SUM(E4:I4)) | M4: =IF(J4="","",IF(K4<>"",K4,N(Job!$B$13))) | N4: =IF(J4="","",IF(L4<>"",L4,N(Job!$B$14))) | O4: =IF(J4="","",J4-P4) | P4: =IF(J4="","",J4/((1+M4)*(1+N4))) | Q4: =IF(J4="","",N(E4)/((1+M4)*(1+N4))) | R4: =IF(J4="","",N(F4)/((1+M4)*(1+N4))) | S4: =IF(J4="","",N(G4)/((1+M4)*(1+N4))) | T4: =IF(J4="","",N(H4)/((1+M4)*(1+N4))) | U4: =IF(J4="","",N(I4)/((1+M4)*(1+N4))) | V4: =IF(OR(J4="",N(D4)=0),"",J4/D4) | W4: =IF(OR(J4="",N(D4)=0),"",P4/D4)
J5: =IF(COUNT(E5:I5)=0,"",SUM(E5:I5)) | M5: =IF(J5="","",IF(K5<>"",K5,N(Job!$B$13))) | N5: =IF(J5="","",IF(L5<>"",L5,N(Job!$B$14))) | O5: =IF(J5="","",J5-P5) | P5: =IF(J5="","",J5/((1+M5)*(1+N5))) | Q5: =IF(J5="","",N(E5)/((1+M5)*(1+N5))) | R5: =IF(J5="","",N(F5)/((1+M5)*(1+N5))) | S5: =IF(J5="","",N(G5)/((1+M5)*(1+N5))) | T5: =IF(J5="","",N(H5)/((1+M5)*(1+N5))) | U5: =IF(J5="","",N(I5)/((1+M5)*(1+N5))) | V5: =IF(OR(J5="",N(D5)=0),"",J5/D5) | W5: =IF(OR(J5="",N(D5)=0),"",P5/D5)
J6: =IF(COUNT(E6:I6)=0,"",SUM(E6:I6)) | M6: =IF(J6="","",IF(K6<>"",K6,N(Job!$B$13))) | N6: =IF(J6="","",IF(L6<>"",L6,N(Job!$B$14))) | O6: =IF(J6="","",J6-P6) | P6: =IF(J6="","",J6/((1+M6)*(1+N6))) | Q6: =IF(J6="","",N(E6)/((1+M6)*(1+N6))) | R6: =IF(J6="","",N(F6)/((1+M6)*(1+N6))) | S6: =IF(J6="","",N(G6)/((1+M6)*(1+N6))) | T6: =IF(J6="","",N(H6)/((1+M6)*(1+N6))) | U6: =IF(J6="","",N(I6)/((1+M6)*(1+N6))) | V6: =IF(OR(J6="",N(D6)=0),"",J6/D6) | W6: =IF(OR(J6="",N(D6)=0),"",P6/D6)
J7: =IF(COUNT(E7:I7)=0,"",SUM(E7:I7)) | M7: =IF(J7="","",IF(K7<>"",K7,N(Job!$B$13))) | N7: =IF(J7="","",IF(L7<>"",L7,N(Job!$B$14))) | O7: =IF(J7="","",J7-P7) | P7: =IF(J7="","",J7/((1+M7)*(1+N7))) | Q7: =IF(J7="","",N(E7)/((1+M7)*(1+N7))) | R7: =IF(J7="","",N(F7)/((1+M7)*(1+N7))) | S7: =IF(J7="","",N(G7)/((1+M7)*(1+N7))) | T7: =IF(J7="","",N(H7)/((1+M7)*(1+N7))) | U7: =IF(J7="","",N(I7)/((1+M7)*(1+N7))) | V7: =IF(OR(J7="",N(D7)=0),"",J7/D7) | W7: =IF(OR(J7="",N(D7)=0),"",P7/D7)
J8: =IF(COUNT(E8:I8)=0,"",SUM(E8:I8)) | M8: =IF(J8="","",IF(K8<>"",K8,N(Job!$B$13))) | N8: =IF(J8="","",IF(L8<>"",L8,N(Job!$B$14))) | O8: =IF(J8="","",J8-P8) | P8: =IF(J8="","",J8/((1+M8)*(1+N8))) | Q8: =IF(J8="","",N(E8)/((1+M8)*(1+N8))) | R8: =IF(J8="","",N(F8)/((1+M8)*(1+N8))) | S8: =IF(J8="","",N(G8)/((1+M8)*(1+N8))) | T8: =IF(J8="","",N(H8)/((1+M8)*(1+N8))) | U8: =IF(J8="","",N(I8)/((1+M8)*(1+N8))) | V8: =IF(OR(J8="",N(D8)=0),"",J8/D8) | W8: =IF(OR(J8="",N(D8)=0),"",P8/D8)
J9: =IF(COUNT(E9:I9)=0,"",SUM(E9:I9)) | M9: =IF(J9="","",IF(K9<>"",K9,N(Job!$B$13))) | N9: =IF(J9="","",IF(L9<>"",L9,N(Job!$B$14))) | O9: =IF(J9="","",J9-P9) | P9: =IF(J9="","",J9/((1+M9)*(1+N9))) | Q9: =IF(J9="","",N(E9)/((1+M9)*(1+N9))) | R9: =IF(J9="","",N(F9)/((1+M9)*(1+N9))) | S9: =IF(J9="","",N(G9)/((1+M9)*(1+N9))) | T9: =IF(J9="","",N(H9)/((1+M9)*(1+N9))) | U9: =IF(J9="","",N(I9)/((1+M9)*(1+N9))) | V9: =IF(OR(J9="",N(D9)=0),"",J9/D9) | W9: =IF(OR(J9="",N(D9)=0),"",P9/D9)
J10: =IF(COUNT(E10:I10)=0,"",SUM(E10:I10)) | M10: =IF(J10="","",IF(K10<>"",K10,N(Job!$B$13))) | N10: =IF(J10="","",IF(L10<>"",L10,N(Job!$B$14))) | O10: =IF(J10="","",J10-P10) | P10: =IF(J10="","",J10/((1+M10)*(1+N10))) | Q10: =IF(J10="","",N(E10)/((1+M10)*(1+N10))) | R10: =IF(J10="","",N(F10)/((1+M10)*(1+N10))) | S10: =IF(J10="","",N(G10)/((1+M10)*(1+N10))) | T10: =IF(J10="","",N(H10)/((1+M10)*(1+N10))) | U10: =IF(J10="","",N(I10)/((1+M10)*(1+N10))) | V10: =IF(OR(J10="",N(D10)=0),"",J10/D10) | W10: =IF(OR(J10="",N(D10)=0),"",P10/D10)
J11: =IF(COUNT(E11:I11)=0,"",SUM(E11:I11)) | M11: =IF(J11="","",IF(K11<>"",K11,N(Job!$B$13))) | N11: =IF(J11="","",IF(L11<>"",L11,N(Job!$B$14))) | O11: =IF(J11="","",J11-P11) | P11: =IF(J11="","",J11/((1+M11)*(1+N11))) | Q11: =IF(J11="","",N(E11)/((1+M11)*(1+N11))) | R11: =IF(J11="","",N(F11)/((1+M11)*(1+N11))) | S11: =IF(J11="","",N(G11)/((1+M11)*(1+N11))) | T11: =IF(J11="","",N(H11)/((1+M11)*(1+N11))) | U11: =IF(J11="","",N(I11)/((1+M11)*(1+N11))) | V11: =IF(OR(J11="",N(D11)=0),"",J11/D11) | W11: =IF(OR(J11="",N(D11)=0),"",P11/D11)
J12: =IF(COUNT(E12:I12)=0,"",SUM(E12:I12)) | M12: =IF(J12="","",IF(K12<>"",K12,N(Job!$B$13))) | N12: =IF(J12="","",IF(L12<>"",L12,N(Job!$B$14))) | O12: =IF(J12="","",J12-P12) | P12: =IF(J12="","",J12/((1+M12)*(1+N12))) | Q12: =IF(J12="","",N(E12)/((1+M12)*(1+N12))) | R12: =IF(J12="","",N(F12)/((1+M12)*(1+N12))) | S12: =IF(J12="","",N(G12)/((1+M12)*(1+N12))) | T12: =IF(J12="","",N(H12)/((1+M12)*(1+N12))) | U12: =IF(J12="","",N(I12)/((1+M12)*(1+N12))) | V12: =IF(OR(J12="",N(D12)=0),"",J12/D12) | W12: =IF(OR(J12="",N(D12)=0),"",P12/D12)
J13: =IF(COUNT(E13:I13)=0,"",SUM(E13:I13)) | M13: =IF(J13="","",IF(K13<>"",K13,N(Job!$B$13))) | N13: =IF(J13="","",IF(L13<>"",L13,N(Job!$B$14))) | O13: =IF(J13="","",J13-P13) | P13: =IF(J13="","",J13/((1+M13)*(1+N13))) | Q13: =IF(J13="","",N(E13)/((1+M13)*(1+N13))) | R13: =IF(J13="","",N(F13)/((1+M13)*(1+N13))) | S13: =IF(J13="","",N(G13)/((1+M13)*(1+N13))) | T13: =IF(J13="","",N(H13)/((1+M13)*(1+N13))) | U13: =IF(J13="","",N(I13)/((1+M13)*(1+N13))) | V13: =IF(OR(J13="",N(D13)=0),"",J13/D13) | W13: =IF(OR(J13="",N(D13)=0),"",P13/D13)
... J400: =IF(COUNT(E400:I400)=0,"",SUM(E400:I400)) | M400: =IF(J400="","",IF(K400<>"",K400,N(Job!$B$13))) | N400: =IF(J400="","",IF(L400<>"",L400,N(Job!$B$14))) | O400: =IF(J400="","",J400-P400) | P400: =IF(J400="","",J400/((1+M400)*(1+N400))) | Q400: =IF(J400="","",N(E400)/((1+M400)*(1+N400))) | R400: =IF(J400="","",N(F400)/((1+M400)*(1+N400))) | S400: =IF(J400="","",N(G400)/((1+M400)*(1+N400))) | T400: =IF(J400="","",N(H400)/((1+M400)*(1+N400))) | U400: =IF(J400="","",N(I400)/((1+M400)*(1+N400))) | V400: =IF(OR(J400="",N(D400)=0),"",J400/D400) | W400: =IF(OR(J400="",N(D400)=0),"",P400/D400)

Sheet Instructions
A1: Bid item budget template
A3: What it’s for | B3: Turning the bid into a working budget. In the app: Jobs → Import budget (new job), or open a job → Import budget lines.
A4: Enter bid prices | B4: On the Budget tab, enter what each bid item was BID at, split into labor, equipment, materials, subcontract and other. These are selling prices — overhead and markup are still in them.
A5: Overhead and markup | B5: Set the default overhead % and markup % on the Job tab. A line with different rates can have its own in the “(line)” columns. The app takes them back out: budget cost = bid price ÷ (1 + overhead %) ÷ (1 + markup %).
A6: Budget cost | B6: The grey columns show the result — the number the job has to be built for, split by labor, equipment, materials, subcontract and other. That is what costs are tracked against in the app.
A7: Example | B7: A $112,000 line with 10% overhead and 12% markup: 112,000 ÷ 1.10 ÷ 1.12 = $90,909 budget cost, $21,091 of overhead and markup.
A8: Quantity and unit | B8: Budget quantity drives % complete: as quantities are installed, the app projects the final cost. Lump-sum lines can be left blank and given a % complete in the app.
A9: Contract amount | B9: Optional on the Job tab. If blank, the contract is the total bid price.
A10: Re-importing | B10: Importing into an existing job only adds lines whose item no. isn’t already there. Nothing is changed or deleted.

Sheet Example
A1: Item no.* | B1: Description* | C1: Unit | D1: Quantity | E1: Labor — bid | F1: Equipment — bid | G1: Materials — bid | H1: Subcontract — bid | I1: Other — bid | J1: Bid price | K1: Overhead % (line) | L1: Markup % (line) | M1: Overhead % used | N1: Markup % used | O1: OH + markup $ | P1: Budget cost | Q1: Labor — budget | R1: Equipment — budget | S1: Materials — budget | T1: Subcontract — budget | U1: Other — budget | V1: Unit bid price | W1: Unit cost | X1: Notes
A2: 1 | B2: Mobilization | C2: LS | D2: 1 | E2: 5544 | F2: 7392 | G2: 0 | H2: 0 | I2: 1848 | J2: =IF(COUNT(E2:I2)=0,"",SUM(E2:I2)) | M2: =IF(J2="","",IF(K2<>"",K2,N(Job!$B$13))) | N2: =IF(J2="","",IF(L2<>"",L2,N(Job!$B$14))) | O2: =IF(J2="","",J2-P2) | P2: =IF(J2="","",J2/((1+M2)*(1+N2))) | Q2: =IF(J2="","",N(E2)/((1+M2)*(1+N2))) | R2: =IF(J2="","",N(F2)/((1+M2)*(1+N2))) | S2: =IF(J2="","",N(G2)/((1+M2)*(1+N2))) | T2: =IF(J2="","",N(H2)/((1+M2)*(1+N2))) | U2: =IF(J2="","",N(I2)/((1+M2)*(1+N2))) | V2: =IF(OR(J2="",N(D2)=0),"",J2/D2) | W2: =IF(OR(J2="",N(D2)=0),"",P2/D2)
A3: 2 | B3: Clearing & grubbing | C3: AC | D3: 14 | E3: 12074 | F3: 20328 | G3: 0 | H3: 0 | I3: 2587 | J3: =IF(COUNT(E3:I3)=0,"",SUM(E3:I3)) | M3: =IF(J3="","",IF(K3<>"",K3,N(Job!$B$13))) | N3: =IF(J3="","",IF(L3<>"",L3,N(Job!$B$14))) | O3: =IF(J3="","",J3-P3) | P3: =IF(J3="","",J3/((1+M3)*(1+N3))) | Q3: =IF(J3="","",N(E3)/((1+M3)*(1+N3))) | R3: =IF(J3="","",N(F3)/((1+M3)*(1+N3))) | S3: =IF(J3="","",N(G3)/((1+M3)*(1+N3))) | T3: =IF(J3="","",N(H3)/((1+M3)*(1+N3))) | U3: =IF(J3="","",N(I3)/((1+M3)*(1+N3))) | V3: =IF(OR(J3="",N(D3)=0),"",J3/D3) | W3: =IF(OR(J3="",N(D3)=0),"",P3/D3)
A4: 3 | B4: Erosion control | C4: LS | D4: 1 | E4: 7638 | F4: 3819 | G4: 14538 | H4: 0 | I4: 0 | J4: =IF(COUNT(E4:I4)=0,"",SUM(E4:I4)) | M4: =IF(J4="","",IF(K4<>"",K4,N(Job!$B$13))) | N4: =IF(J4="","",IF(L4<>"",L4,N(Job!$B$14))) | O4: =IF(J4="","",J4-P4) | P4: =IF(J4="","",J4/((1+M4)*(1+N4))) | Q4: =IF(J4="","",N(E4)/((1+M4)*(1+N4))) | R4: =IF(J4="","",N(F4)/((1+M4)*(1+N4))) | S4: =IF(J4="","",N(G4)/((1+M4)*(1+N4))) | T4: =IF(J4="","",N(H4)/((1+M4)*(1+N4))) | U4: =IF(J4="","",N(I4)/((1+M4)*(1+N4))) | V4: =IF(OR(J4="",N(D4)=0),"",J4/D4) | W4: =IF(OR(J4="",N(D4)=0),"",P4/D4)
A5: 4 | B5: Mass excavation | C5: CY | D5: 48000 | E5: 76877 | F5: 186278 | G5: 0 | H5: 0 | I5: 0 | J5: =IF(COUNT(E5:I5)=0,"",SUM(E5:I5)) | M5: =IF(J5="","",IF(K5<>"",K5,N(Job!$B$13))) | N5: =IF(J5="","",IF(L5<>"",L5,N(Job!$B$14))) | O5: =IF(J5="","",J5-P5) | P5: =IF(J5="","",J5/((1+M5)*(1+N5))) | Q5: =IF(J5="","",N(E5)/((1+M5)*(1+N5))) | R5: =IF(J5="","",N(F5)/((1+M5)*(1+N5))) | S5: =IF(J5="","",N(G5)/((1+M5)*(1+N5))) | T5: =IF(J5="","",N(H5)/((1+M5)*(1+N5))) | U5: =IF(J5="","",N(I5)/((1+M5)*(1+N5))) | V5: =IF(OR(J5="",N(D5)=0),"",J5/D5) | W5: =IF(OR(J5="",N(D5)=0),"",P5/D5)
A6: 5 | B6: 24" RCP storm pipe | C6: LF | D6: 1200 | E6: 26611 | F6: 17741 | G6: 72442 | H6: 0 | I6: 0 | J6: =IF(COUNT(E6:I6)=0,"",SUM(E6:I6)) | M6: =IF(J6="","",IF(K6<>"",K6,N(Job!$B$13))) | N6: =IF(J6="","",IF(L6<>"",L6,N(Job!$B$14))) | O6: =IF(J6="","",J6-P6) | P6: =IF(J6="","",J6/((1+M6)*(1+N6))) | Q6: =IF(J6="","",N(E6)/((1+M6)*(1+N6))) | R6: =IF(J6="","",N(F6)/((1+M6)*(1+N6))) | S6: =IF(J6="","",N(G6)/((1+M6)*(1+N6))) | T6: =IF(J6="","",N(H6)/((1+M6)*(1+N6))) | U6: =IF(J6="","",N(I6)/((1+M6)*(1+N6))) | V6: =IF(OR(J6="",N(D6)=0),"",J6/D6) | W6: =IF(OR(J6="",N(D6)=0),"",P6/D6)
A7: 6 | B7: Graded aggregate base 8" | C7: SY | D7: 9500 | E7: 11704 | F7: 14045 | G7: 81928 | H7: 0 | I7: 0 | J7: =IF(COUNT(E7:I7)=0,"",SUM(E7:I7)) | M7: =IF(J7="","",IF(K7<>"",K7,N(Job!$B$13))) | N7: =IF(J7="","",IF(L7<>"",L7,N(Job!$B$14))) | O7: =IF(J7="","",J7-P7) | P7: =IF(J7="","",J7/((1+M7)*(1+N7))) | Q7: =IF(J7="","",N(E7)/((1+M7)*(1+N7))) | R7: =IF(J7="","",N(F7)/((1+M7)*(1+N7))) | S7: =IF(J7="","",N(G7)/((1+M7)*(1+N7))) | T7: =IF(J7="","",N(H7)/((1+M7)*(1+N7))) | U7: =IF(J7="","",N(I7)/((1+M7)*(1+N7))) | V7: =IF(OR(J7="",N(D7)=0),"",J7/D7) | W7: =IF(OR(J7="",N(D7)=0),"",P7/D7)
A8: 7 | B8: Asphalt paving (sub) | C8: SY | D8: 9500 | E8: 0 | F8: 0 | G8: 0 | H8: 156209 | I8: 0 | J8: =IF(COUNT(E8:I8)=0,"",SUM(E8:I8)) | K8: 0.05 | L8: 0.08 | M8: =IF(J8="","",IF(K8<>"",K8,N(Job!$B$13))) | N8: =IF(J8="","",IF(L8<>"",L8,N(Job!$B$14))) | O8: =IF(J8="","",J8-P8) | P8: =IF(J8="","",J8/((1+M8)*(1+N8))) | Q8: =IF(J8="","",N(E8)/((1+M8)*(1+N8))) | R8: =IF(J8="","",N(F8)/((1+M8)*(1+N8))) | S8: =IF(J8="","",N(G8)/((1+M8)*(1+N8))) | T8: =IF(J8="","",N(H8)/((1+M8)*(1+N8))) | U8: =IF(J8="","",N(I8)/((1+M8)*(1+N8))) | V8: =IF(OR(J8="",N(D8)=0),"",J8/D8) | W8: =IF(OR(J8="",N(D8)=0),"",P8/D8)
